openaleph_procrastinate/__init__.py
openaleph_procrastinate/app.py
openaleph_procrastinate/archive.py
openaleph_procrastinate/asgi.py
openaleph_procrastinate/cli.py
openaleph_procrastinate/defer.py
openaleph_procrastinate/exceptions.py
openaleph_procrastinate/helpers.py
openaleph_procrastinate/manage/__init__.py
openaleph_procrastinate/manage/db.py
openaleph_procrastinate/manage/sql.py
openaleph_procrastinate/manage/status.py
openaleph_procrastinate/model.py
openaleph_procrastinate/settings.py
openaleph_procrastinate/tasks.py
openaleph_procrastinate/urls.py
openaleph_procrastinate/util.py
openaleph_procrastinate/wsgi.py
openaleph_procrastinate-5.1.2.dist-info/LICENSE
openaleph_procrastinate-5.1.2.dist-info/METADATA
openaleph_procrastinate-5.1.2.dist-info/NOTICE
openaleph_procrastinate-5.1.2.dist-info/WHEEL
openaleph_procrastinate-5.1.2.dist-info/entry_points.txt
openaleph_procrastinate-5.1.2.dist-info/RECORD
