Metadata-Version: 2.3
Name: openaleph-procrastinate
Version: 5.1.2
Summary: Task queue logic for OpenAleph built upon procrastinate
License: AGPLv3+
Author: Simon Wörpel
Author-email: simon.woerpel@pm.me
Requires-Python: >=3.11,<4
Classifier: Intended Audience :: Developers
Classifier: Operating System :: OS Independent
Classifier: Programming Language :: Python
Classifier: Programming Language :: Python :: 3.11
Classifier: Programming Language :: Python :: 3.12
Classifier: Programming Language :: Python :: 3.13
Requires-Dist: anystore (>=0.4.0,<0.5.0)
Requires-Dist: cachetools (<6)
Requires-Dist: followthemoney (>=4.3.2,<5.0.0)
Requires-Dist: ftmq (>=4.3.2,<5.0.0)
Requires-Dist: procrastinate (>=3.5.3,<4.0.0)
Requires-Dist: psycopg (>=3.2.11,<4.0.0)
Requires-Dist: pydantic (>=2.11.7,<3.0.0)
Requires-Dist: pydantic-settings (>=2.10.1,<3.0.0)
Project-URL: Documentation, https://github.com/openaleph/openaleph-procrastinate
Project-URL: Homepage, https://github.com/openaleph/openaleph-procrastinate
Project-URL: Issues, https://github.com/openaleph/openaleph-procrastinate/issues
Project-URL: Repository, https://github.com/openaleph/openaleph-procrastinate
